README.rst
george_ess.py
setup.py
george_ess.egg-info/PKG-INFO
george_ess.egg-info/SOURCES.txt
george_ess.egg-info/dependency_links.txt
george_ess.egg-info/top_level.txt