Metadata-Version: 1.1
Name: george-ess
Version: 0.0.1
Summary: Elliptical slice sampling for George
Home-page: https://github.com/dfm/george-ess
Author: Daniel Foreman-Mackey
Author-email: danfm@nyu.edu
License: MIT
Platform: UNKNOWN
Classifier: Intended Audience :: Developers
Classifier: Intended Audience :: Science/Research
Classifier: License :: OSI Approved :: MIT License
Classifier: Operating System :: OS Independent
Classifier: Programming Language :: Python
